setup.py
cow/__init__.py
cow/server.py
cow/testing.py
cow/handlers/__init__.py
cow/handlers/healthcheck.py
cow/plugins/__init__.py
cow/plugins/es_plugin.py
cow/plugins/gandalf_plugin.py
cow/plugins/geopy_google_plugin.py
cow/plugins/mongoengine_plugin.py
cow/plugins/motor_plugin.py
cow/plugins/motorengine_plugin.py
cow/plugins/pusher_plugin.py
cow/plugins/redis_plugin.py
cow/plugins/sqlalchemy_plugin.py
cow/plugins/sync_redis_plugin.py
cow_framework.egg-info/PKG-INFO
cow_framework.egg-info/SOURCES.txt
cow_framework.egg-info/dependency_links.txt
cow_framework.egg-info/entry_points.txt
cow_framework.egg-info/requires.txt
cow_framework.egg-info/top_level.txt
tests/__init__.py
tests/test_healthcheck.py
tests/test_server.py
tests/sandbox/__init__.py
tests/sandbox/server.py
tests/sandbox/config/__init__.py
tests/sandbox/handlers/__init__.py
tests/sandbox/handlers/test.py