Metadata-Version: 1.1
Name: cow-framework
Version: 1.0.2
Summary: cow is a quick-start for tornado-powered applications (specially for apis).
Home-page: http://github.com/heynemann/cow/
Author: Bernardo Heynemann
Author-email: heynemann@gmail.com
License: MIT
Keywords: web framework tornado python
Platform: UNKNOWN
Classifier: Development Status :: 4 - Beta
Classifier: Intended Audience :: Developers
Classifier: License :: OSI Approved :: MIT License
Classifier: Natural Language :: English
Classifier: Operating System :: MacOS
Classifier: Operating System :: POSIX
Classifier: Operating System :: Unix
Classifier: Operating System :: OS Independent
Classifier: Programming Language :: Python :: 2.6
Classifier: Programming Language :: Python :: 2.7
